{
  "db_name": "PostgreSQL",
  "query": "INSERT INTO courses (course_code, display_name, program_code) VALUES ($1, $2, $3) RETURNING *",
  "describe": {
    "columns": [
      {
        "ordinal": 0,
        "name": "course_code",
        "type_info": "Varchar"
      },
      {
        "ordinal": 1,
        "name": "display_name",
        "type_info": "Varchar"
      },
      {
        "ordinal": 2,
        "name": "program_code",
        "type_info": "Varchar"
      },
      {
        "ordinal": 3,
        "name": "specialization_code",
        "type_info": "Varchar"
      }
    ],
    "parameters": {
      "Left": [
        "Varchar",
        "Varchar",
        "Varchar"
      ]
    },
    "nullable": [
      false,
      false,
      false,
      true
    ]
  },
  "hash": "3fd271d33db65d33523aad0b6a9c5c343ee22c4d1d2108852530b2e53e1bab6d"
}
